djangorestframework_simplejwt_casng/__init__.py
djangorestframework_simplejwt_casng/serializers.py
djangorestframework_simplejwt_casng/views.py
djangorestframework_simplejwt_casng-0.0.2.dist-info/LICENSE
djangorestframework_simplejwt_casng-0.0.2.dist-info/METADATA
djangorestframework_simplejwt_casng-0.0.2.dist-info/WHEEL
djangorestframework_simplejwt_casng-0.0.2.dist-info/top_level.txt
djangorestframework_simplejwt_casng-0.0.2.dist-info/RECORD
