Metadata-Version: 2.1
Name: djangorestframework-simplejwt-casng
Version: 0.0.2
Summary: A JSON Web Token authentication plugin for the Django REST Framework, integrated with CAS Authentication.
Home-page: https://github.com/ChangshengYan/djangorestframework-simplejwt-casng
Author: Changsheng Yan
Author-email: cs.yan@outlook.com
License: UNKNOWN
Platform: UNKNOWN
Classifier: Programming Language :: Python :: 3
Classifier: License :: OSI Approved :: MIT License
Classifier: Operating System :: OS Independent
Requires-Python: >=3.6
Requires-Dist: django (>=3.0)
Requires-Dist: django-cas-ng
Requires-Dist: djangorestframework
Requires-Dist: djangorestframework-simplejwt
